{
  "version": 2,
  "extractor": "pdffigures2",
  "figures": [
    {
      "url": "assets/figures/arxiv/2605.10571v1/fig-001.webp",
      "caption": "Table 1. Main quantitative results for in-domain (STONE) and three cardiac MRI datasets. σlog |J| ≡ std(log det J) × 10−2. - indicates not applicable due to sequence",
      "page": 7,
      "index": 1,
      "width": 729,
      "height": 329
    },
    {
      "url": "assets/figures/arxiv/2605.10571v1/fig-002.webp",
      "caption": "Fig. 3. T1 mapping quality on STONE (LV+Myo). (a) Slice-wise mean R2. Slice position: base (0) to apex (4). Any2Reg IO demonstrates the best alignment at all slice positions. (b) R2 survival curves show Any2Reg has consistently higher fitting quality as a result of superior alignment.",
      "page": 7,
      "index": 2,
      "width": 723,
      "height": 208
    },
    {
      "url": "assets/figures/arxiv/2605.10571v1/fig-003.webp",
      "caption": "Fig. 2. Comparison of two learning-based groupwise registration designs: (a) The conventional channel stacking design concatenates frames; it is order-sensitive (fθ(π · Iseq) ̸= π · fθ(Iseq)) and tied to a fixed length L. (b) Set-based design (Any2Reg) uses shared encoders and a canonical reference T = Γ (I) broadcasted to all frames; it enables permutation-equivariant registration (R(π · I) = π · R(I)) for an arbitrary L.",
      "page": 4,
      "index": 3,
      "width": 732,
      "height": 341
    },
    {
      "url": "assets/figures/arxiv/2605.10571v1/fig-004.webp",
      "caption": "Fig. 4. Qualitative result on a representative STONE sequence with T1 map, fitting uncertainty SDT1 (↓), and pixelwise fitting R2 (↑). White arrows indicate the location of large motion. Both Any2Reg and Any2Reg IO yield clear T1 maps with high precision.",
      "page": 8,
      "index": 4,
      "width": 725,
      "height": 275
    }
  ]
}