{
  "version": 2,
  "extractor": "pdffigures2",
  "figures": [
    {
      "url": "assets/figures/arxiv/2604.10910v2/fig-001.webp",
      "caption": "Fig. 1. The visual comparison of utilizing different deformation fields for Gaussian-based video representation. The results show that our method better represent both background details and motion patterns.",
      "page": 1,
      "index": 1,
      "width": 529,
      "height": 341
    },
    {
      "url": "assets/figures/arxiv/2604.10910v2/fig-002.webp",
      "caption": "Fig. 8. Visual comparison of static hash encoding and dynamic encoding in bosphorus dataset. Our method achieves the best quality in the dynamic region (red block) and the static region (yellow block).",
      "page": 6,
      "index": 2,
      "width": 529,
      "height": 295
    },
    {
      "url": "assets/figures/arxiv/2604.10910v2/fig-003.webp",
      "caption": "Fig. 11. Visualization of reconstruction quality on Jockey, Readysteaygo, and Camel (from top to bottom).",
      "page": 11,
      "index": 3,
      "width": 1076,
      "height": 658
    },
    {
      "url": "assets/figures/arxiv/2604.10910v2/fig-004.webp",
      "caption": "Fig. 10. Visualization of video denoising.",
      "page": 10,
      "index": 4,
      "width": 1076,
      "height": 500
    },
    {
      "url": "assets/figures/arxiv/2604.10910v2/fig-005.webp",
      "caption": "Fig. 2. Overall of our proposed method STGV. We first select the first frame from a GoP as the key-frame to perform coarse training to construct the canonical space. Then, the canonical space is trained jointly with the spatio-temporal hash encoding to obtain the deformed attributes of Gaussians at each frame. Finally, the Gaussian attributes of canonical space and the frame-specific Gaussian deformation are combined and rendered to generate the corresponding frame.",
      "page": 3,
      "index": 5,
      "width": 1076,
      "height": 350
    },
    {
      "url": "assets/figures/arxiv/2604.10910v2/fig-006.webp",
      "caption": "Fig. 3. The visual comparison between Key Frame Canonical and Multi-frame Initialization upon canonical space.",
      "page": 3,
      "index": 6,
      "width": 529,
      "height": 322
    },
    {
      "url": "assets/figures/arxiv/2604.10910v2/fig-007.webp",
      "caption": "Fig. 4. Visual comparison results. From left to right are yachtride, cows and boat video. Benefiting from Spatio-Temporal hash encoding and KFCI strategy, our methods achieves best visual quality.",
      "page": 4,
      "index": 7,
      "width": 1076,
      "height": 291
    },
    {
      "url": "assets/figures/arxiv/2604.10910v2/fig-008.webp",
      "caption": "TABLE I QUANTITATIVE RESULTS COMPARISON ON UVG AND DAVIS DATASET. BOLD INDICATES THE BEST PERFORMANCE, AND UNDERLINE INDICATES THE SECOND BEST.",
      "page": 4,
      "index": 8,
      "width": 523,
      "height": 299
    },
    {
      "url": "assets/figures/arxiv/2604.10910v2/fig-009.webp",
      "caption": "TABLE VI VIDEO DENOISING PERFORMANCE. PSNR IS RECORDED IN DB.",
      "page": 9,
      "index": 9,
      "width": 521,
      "height": 252
    },
    {
      "url": "assets/figures/arxiv/2604.10910v2/fig-010.webp",
      "caption": "Fig. 9. Results with different Gaussian Numbers.",
      "page": 9,
      "index": 10,
      "width": 515,
      "height": 303
    },
    {
      "url": "assets/figures/arxiv/2604.10910v2/fig-011.webp",
      "caption": "Fig. 5. Compression results on Bunny dataset.",
      "page": 5,
      "index": 11,
      "width": 529,
      "height": 345
    },
    {
      "url": "assets/figures/arxiv/2604.10910v2/fig-012.webp",
      "caption": "Fig. 6. Video inpainting visualization on cows and blackswan.",
      "page": 5,
      "index": 12,
      "width": 529,
      "height": 273
    },
    {
      "url": "assets/figures/arxiv/2604.10910v2/fig-013.webp",
      "caption": "Fig. 7. The spatial interpolation visualization on Beauty and Honeybee.",
      "page": 5,
      "index": 13,
      "width": 529,
      "height": 260
    }
  ]
}