{
  "version": 2,
  "extractor": "pdffigures2",
  "figures": [
    {
      "url": "assets/figures/arxiv/2603.22509v1/fig-001.webp",
      "caption": "Figure 3. Qualitative comparison of baseline methods. For each case, we extract a sketch and text description from the ground-truth mask to encode organ geometry. These features guide the generation of 3D masks and the synthesis of 3D volumes.",
      "page": 8,
      "index": 1,
      "width": 1027,
      "height": 413
    },
    {
      "url": "assets/figures/arxiv/2603.22509v1/fig-002.webp",
      "caption": "Figure 2. Overview of our Sketch2CT framework. (a) A capsule-based sketch encoder and a sentence transformer extract structural and semantic features, which are fused via a FiLM module. (b) The fused representation conditions a segmentation latent diffusion model to generate 3D organ masks. (c) The predicted segmentation latent guides an image latent diffusion model to synthesize 3D medical volumes.",
      "page": 4,
      "index": 2,
      "width": 906,
      "height": 654
    }
  ]
}